Metadata-Version: 2.1
Name: pyminifier-ls
Version: 2.3
Summary: Python code minifier, obfuscator, and compressor
Home-page: https://github.com/liftoff/pyminifier
Author: Dan McDougall <daniel.mcdougall@liftoffsoftware.com>
Author-email: daniel.mcdougall@liftoffsoftware.com
License: Proprietary
Platform: UNKNOWN
Classifier: Environment :: Console
Classifier: Intended Audience :: Developers
Classifier: Intended Audience :: System Administrators
Classifier: Programming Language :: Python
Classifier: Programming Language :: Python :: 3.7
Classifier: Programming Language :: Python :: 3.8
Classifier: Programming Language :: Python :: 3.9
Classifier: Programming Language :: Python :: 3.10
Classifier: License :: OSI Approved :: GNU Affero General Public License v3
Classifier: Topic :: Software Development :: Build Tools
Classifier: Topic :: Software Development :: Libraries :: Python Modules
Provides: pyminifier
License-File: LICENSE
